multiversum/IPCKernelManager.py
multiversum/__init__.py
multiversum/__main__.py
multiversum/cli_helpers.py
multiversum/helpers.py
multiversum/logger.py
multiversum/multiverse.py
multiversum/parallel.py
multiversum/universe.py
multiversum-0.7.2.dist-info/licenses/LICENSE
multiversum-0.7.2.dist-info/METADATA
multiversum-0.7.2.dist-info/WHEEL
multiversum-0.7.2.dist-info/entry_points.txt
multiversum-0.7.2.dist-info/top_level.txt
multiversum-0.7.2.dist-info/RECORD
