Metadata-Version: 2.4
Name: multiversum
Version: 0.7.2
Summary: A helper package to conduct multiverse analyses in Python
Author: Jan Simson
License: Apache-2.0
Project-URL: Homepage, https://github.com/jansim/multiversum
Project-URL: Changelog, https://github.com/jansim/multiversum/releases
Project-URL: Issues, https://github.com/jansim/multiversum/issues
Project-URL: CI, https://github.com/jansim/multiversum/actions
Classifier: License :: OSI Approved :: Apache Software License
Requires-Python: >=3.8
License-File: LICENSE
Requires-Dist: pandas
Requires-Dist: papermill
Requires-Dist: joblib
Requires-Dist: ipykernel
Requires-Dist: tomli>=1.1.0; python_version < "3.11"
Requires-Dist: click
Requires-Dist: rich
Provides-Extra: test
Requires-Dist: pytest; extra == "test"
Requires-Dist: ruff; extra == "test"
Provides-Extra: docs
Requires-Dist: mkdocs; extra == "docs"
Requires-Dist: mkdocs-material; extra == "docs"
Requires-Dist: mkdocstrings[python]; extra == "docs"
Requires-Dist: mkdocs-click; extra == "docs"
Dynamic: license-file
